caselaw_tools/__init__.py
caselaw_tools/caselaw_tools.py
caselaw_tools/tests/__init__.py
caselaw_tools/tests/test_hello.py
caselaw_tools-0.2.0.dist-info/LICENSE
caselaw_tools-0.2.0.dist-info/METADATA
caselaw_tools-0.2.0.dist-info/WHEEL
caselaw_tools-0.2.0.dist-info/top_level.txt
caselaw_tools-0.2.0.dist-info/RECORD
