Metadata-Version: 2.1
Name: caselaw-tools
Version: 0.2.0
Summary: Python toolkit for working with case law
Home-page: https://github.com/horninc/caselaw_tools
Author: Kristaps Horns
Author-email: k.horns@ideaspool.nl
License: UNKNOWN
Project-URL: Bug Reports, https://github.com/horninc/caselaw_tools/issues
Project-URL: Source, https://github.com/horninc/caselaw_tools
Keywords: caselaw tools cjeu
Platform: UNKNOWN
Classifier: Development Status :: 3 - Alpha
Classifier: Intended Audience :: Developers
Classifier: License :: OSI Approved :: GNU General Public License v3 or later (GPLv3+)
Classifier: Programming Language :: Python :: 3.6
Classifier: Programming Language :: Python :: 3.7
Classifier: Programming Language :: Python :: 3.8
Requires-Python: >=3.6, <4
Requires-Dist: numpy
Requires-Dist: pytz
Requires-Dist: tqdm
Requires-Dist: pandas
Requires-Dist: requests
Requires-Dist: lxml
